MANIFEST.in
README.rst
setup.py
ckanext/__init__.py
ckanext/salford/__init__.py
ckanext/salford/plugin.py
ckanext/salford/fanstatic/bower.json
ckanext/salford/fanstatic/bower_components/twitter-fetcher/.bower.json
ckanext/salford/fanstatic/bower_components/twitter-fetcher/bower.json
ckanext/salford/fanstatic/bower_components/twitter-fetcher/index.html
ckanext/salford/fanstatic/bower_components/twitter-fetcher/css/style.css
ckanext/salford/fanstatic/bower_components/twitter-fetcher/js/exampleUsage.js
ckanext/salford/fanstatic/bower_components/twitter-fetcher/js/twitterFetcher.js
ckanext/salford/fanstatic/bower_components/twitter-fetcher/js/twitterFetcher_min.js
ckanext/salford/fanstatic/css/theme.css
ckanext/salford/fanstatic/js/home.js
ckanext/salford/fanstatic/less/theme.less
ckanext/salford/public/licenses.json
ckanext/salford/templates/base.html
ckanext/salford/templates/footer.html
ckanext/salford/templates/header.html
ckanext/salford/templates/publication_scheme.html
ckanext/salford/templates/group/snippets/group_item.html
ckanext/salford/templates/group/snippets/group_list.html
ckanext/salford/templates/home/index.html
ckanext/salford/templates/organization/snippets/organization_item.html
ckanext/salford/templates/organization/snippets/organization_list.html
ckanext/salford/templates/package/read_base.html
ckanext/salford/templates/package/snippets/additional_info.html
ckanext/salford/templates/package/snippets/package_basic_fields.html
ckanext/salford/templates/package/snippets/package_metadata_fields.html
ckanext/salford/tests/__init__.py
ckanext/salford/tests/test_plugin.py
ckanext_salford.egg-info/PKG-INFO
ckanext_salford.egg-info/SOURCES.txt
ckanext_salford.egg-info/dependency_links.txt
ckanext_salford.egg-info/entry_points.txt
ckanext_salford.egg-info/top_level.txt